deltaforge/DeltaDataframeHelper.py
deltaforge/__init__.py
deltaforge-1.2.2.dist-info/LICENSE
deltaforge-1.2.2.dist-info/METADATA
deltaforge-1.2.2.dist-info/WHEEL
deltaforge-1.2.2.dist-info/entry_points.txt
deltaforge-1.2.2.dist-info/top_level.txt
deltaforge-1.2.2.dist-info/RECORD
