Metadata-Version: 2.1
Name: deltaforge
Version: 1.2.2
Summary: Support common PySpark operations on Delta
Author-email: Andrij Demianczuk <andrij.demianczuk@databricks.com>
License: Apache License
Project-URL: Homepage, https://www.databricks.com/
Keywords: delta,pyspark,spark
Classifier: License :: OSI Approved :: Apache Software License
Classifier: Programming Language :: Python
Classifier: Programming Language :: Python :: 3
Requires-Python: >=3.10
License-File: LICENSE
Provides-Extra: dev
Requires-Dist: black ; extra == 'dev'
Requires-Dist: pip-tools ; extra == 'dev'
Requires-Dist: pytest ; extra == 'dev'
Requires-Dist: bumpver ; extra == 'dev'
